HVImpactScore/HVImpactScore.py
HVImpactScore-1.0.5.dist-info/METADATA
HVImpactScore-1.0.5.dist-info/WHEEL
HVImpactScore-1.0.5.dist-info/top_level.txt
HVImpactScore-1.0.5.dist-info/RECORD
