Metadata-Version: 2.1
Name: HVImpactScore
Version: 1.0.5
Summary: Similarity scoring method for hypervelocity impact simulations using smoothed particle hydrodynamics
Author-email: Stephen Marinsek <smarins1@jhu.edu>
Project-URL: Homepage, https://github.com/smarinsek/HVImpactScore
Classifier: Programming Language :: Python :: 3
Classifier: License :: OSI Approved :: MIT License
Classifier: Operating System :: OS Independent
Requires-Python: >=3.8
